tiny_ai_helper/Model.py
tiny_ai_helper/__init__.py
tiny_ai_helper/csv.py
tiny_ai_helper/layers.py
tiny_ai_helper/utils.py
tiny_ai_helper-0.1.15.dist-info/LICENSE
tiny_ai_helper-0.1.15.dist-info/METADATA
tiny_ai_helper-0.1.15.dist-info/WHEEL
tiny_ai_helper-0.1.15.dist-info/top_level.txt
tiny_ai_helper-0.1.15.dist-info/RECORD
