Metadata-Version: 2.1
Name: tiny-ai-helper
Version: 0.1.15
Summary: Tiny AI Helper for PyTorch
Home-page: https://github.com/bayrell/ai_helper
Author: Ildar Bikmamatov
Author-email: support@bayrell.org
License: MIT License
Keywords: ai helper,pytorch
Platform: UNKNOWN
Classifier: License :: OSI Approved :: MIT License
Classifier: Operating System :: POSIX :: Linux
Classifier: Operating System :: Microsoft :: Windows :: Windows 10
Classifier: Programming Language :: Python
Classifier: Programming Language :: Python :: 3
Classifier: Programming Language :: Python :: 3.8
Classifier: Topic :: Scientific/Engineering :: Artificial Intelligence
License-File: LICENSE
